[
 {
  "amount": 450.0, 
  "base_amount": 450.0, 
  "base_net_amount": 450.0, 
  "base_net_rate": 450.0, 
  "base_price_list_rate": 450.0, 
  "base_rate": 450.0, 
  "billed_amt": 0.0, 
  "bom": null, 
  "brand": "HP", 
  "conversion_factor": 1.0, 
  "delivered_by_supplier": 0, 
  "description": "PORT\u00c1TIL HP", 
  "discount": 0.0, 
  "discount_percentage": 0.0, 
  "docstatus": 1, 
  "doctype": "Purchase Order Item", 
  "expected_delivery_date": null, 
  "image": "", 
  "item_code": "HP-COREI3", 
  "item_group": "Productos", 
  "item_name": "HP-COREI3", 
  "item_tax_rate": "{}", 
  "material_request": null, 
  "material_request_item": null, 
  "modified": "2017-06-05 17:37:51.797924", 
  "name": "8a16e11758", 
  "net_amount": 450.0, 
  "net_rate": 450.0, 
  "page_break": 0, 
  "price_list_rate": 450.0, 
  "pricing_rule": null, 
  "project": null, 
  "qty": 1.0, 
  "rate": 450.0, 
  "received_qty": 0.0, 
  "returned_qty": 0.0, 
  "sales_order": null, 
  "sales_order_item": null, 
  "schedule_date": "2017-06-02", 
  "stock_qty": 1.0, 
  "stock_uom": "Unidad(es)", 
  "subtotal": 0.0, 
  "supplier_part_no": null, 
  "supplier_quotation": null, 
  "supplier_quotation_item": null, 
  "unit_price": 0.0, 
  "unit_price_with_no_dcto": 0.0, 
  "unit_price_with_tax": 0.0, 
  "uom": "Unidad(es)", 
  "warehouse": "Sucursales - ET"
 }, 
 {
  "amount": 12.0, 
  "base_amount": 12.0, 
  "base_net_amount": 12.0, 
  "base_net_rate": 12.0, 
  "base_price_list_rate": 12.0, 
  "base_rate": 12.0, 
  "billed_amt": 0.0, 
  "bom": null, 
  "brand": "GENIUS", 
  "conversion_factor": 1.0, 
  "delivered_by_supplier": 0, 
  "description": "MOUSE GENIUS", 
  "discount": 0.0, 
  "discount_percentage": 0.0, 
  "docstatus": 1, 
  "doctype": "Purchase Order Item", 
  "expected_delivery_date": null, 
  "image": "", 
  "item_code": "PM0001", 
  "item_group": "Productos", 
  "item_name": "MOUSE GENIUS", 
  "item_tax_rate": "{}", 
  "material_request": null, 
  "material_request_item": null, 
  "modified": "2017-06-06 12:12:54.979190", 
  "name": "ebd79d3dbb", 
  "net_amount": 12.0, 
  "net_rate": 12.0, 
  "page_break": 0, 
  "price_list_rate": 12.0, 
  "pricing_rule": null, 
  "project": null, 
  "qty": 1.0, 
  "rate": 12.0, 
  "received_qty": 0.0, 
  "returned_qty": 0.0, 
  "sales_order": null, 
  "sales_order_item": null, 
  "schedule_date": "2017-06-01", 
  "stock_qty": 1.0, 
  "stock_uom": "Unidad(es)", 
  "subtotal": 0.0, 
  "supplier_part_no": null, 
  "supplier_quotation": null, 
  "supplier_quotation_item": null, 
  "unit_price": 0.0, 
  "unit_price_with_no_dcto": 0.0, 
  "unit_price_with_tax": 0.0, 
  "uom": "Unidad(es)", 
  "warehouse": "Sucursales - ET"
 }, 
 {
  "amount": 12.0, 
  "base_amount": 12.0, 
  "base_net_amount": 12.0, 
  "base_net_rate": 12.0, 
  "base_price_list_rate": 12.0, 
  "base_rate": 12.0, 
  "billed_amt": 0.0, 
  "bom": null, 
  "brand": "GENIUS", 
  "conversion_factor": 1.0, 
  "delivered_by_supplier": 0, 
  "description": "MOUSE GENIUS", 
  "discount": 0.0, 
  "discount_percentage": 0.0, 
  "docstatus": 1, 
  "doctype": "Purchase Order Item", 
  "expected_delivery_date": null, 
  "image": "", 
  "item_code": "PM0001", 
  "item_group": "Productos", 
  "item_name": "MOUSE GENIUS", 
  "item_tax_rate": "{}", 
  "material_request": null, 
  "material_request_item": null, 
  "modified": "2017-06-06 11:53:20.633499", 
  "name": "06cbbb18e1", 
  "net_amount": 12.0, 
  "net_rate": 12.0, 
  "page_break": 0, 
  "price_list_rate": 12.0, 
  "pricing_rule": null, 
  "project": null, 
  "qty": 1.0, 
  "rate": 12.0, 
  "received_qty": 0.0, 
  "returned_qty": 0.0, 
  "sales_order": null, 
  "sales_order_item": null, 
  "schedule_date": "2017-06-06", 
  "stock_qty": 1.0, 
  "stock_uom": "Unidad(es)", 
  "subtotal": 12.0, 
  "supplier_part_no": null, 
  "supplier_quotation": null, 
  "supplier_quotation_item": null, 
  "unit_price": 12.0, 
  "unit_price_with_no_dcto": 12.0, 
  "unit_price_with_tax": 17.784, 
  "uom": "Unidad(es)", 
  "warehouse": "Sucursales - ET"
 }, 
 {
  "amount": 0.0, 
  "base_amount": 0.0, 
  "base_net_amount": 0.0, 
  "base_net_rate": 0.0, 
  "base_price_list_rate": 0.0, 
  "base_rate": 0.0, 
  "billed_amt": 0.0, 
  "bom": null, 
  "brand": null, 
  "conversion_factor": 1.0, 
  "delivered_by_supplier": 0, 
  "description": "PORT\u00c1TIL DELL", 
  "discount": 0.0, 
  "discount_percentage": 0.0, 
  "docstatus": 1, 
  "doctype": "Purchase Order Item", 
  "expected_delivery_date": null, 
  "image": "", 
  "item_code": "PORT\u00c1TIL DELL", 
  "item_group": "Productos", 
  "item_name": "PORT\u00c1TIL DELL", 
  "item_tax_rate": "{}", 
  "material_request": null, 
  "material_request_item": null, 
  "modified": "2017-06-06 11:53:20.633499", 
  "name": "aad4d4ab39", 
  "net_amount": 0.0, 
  "net_rate": 0.0, 
  "page_break": 0, 
  "price_list_rate": 0.0, 
  "pricing_rule": null, 
  "project": null, 
  "qty": 2.0, 
  "rate": 0.0, 
  "received_qty": 0.0, 
  "returned_qty": 0.0, 
  "sales_order": null, 
  "sales_order_item": null, 
  "schedule_date": "2017-06-06", 
  "stock_qty": 2.0, 
  "stock_uom": "Unidad(es)", 
  "subtotal": 1000.0, 
  "supplier_part_no": null, 
  "supplier_quotation": null, 
  "supplier_quotation_item": null, 
  "unit_price": 500.0, 
  "unit_price_with_no_dcto": 500.0, 
  "unit_price_with_tax": 741.0, 
  "uom": "Unidad(es)", 
  "warehouse": "Productos terminados - ET"
 }, 
 {
  "amount": 36.0, 
  "base_amount": 36.0, 
  "base_net_amount": 36.0, 
  "base_net_rate": 12.0, 
  "base_price_list_rate": 12.0, 
  "base_rate": 12.0, 
  "billed_amt": 0.0, 
  "bom": null, 
  "brand": "GENIUS", 
  "conversion_factor": 1.0, 
  "delivered_by_supplier": 0, 
  "description": "MOUSE GENIUS", 
  "discount": 0.0, 
  "discount_percentage": 0.0, 
  "docstatus": 1, 
  "doctype": "Purchase Order Item", 
  "expected_delivery_date": null, 
  "image": "", 
  "item_code": "PM0001", 
  "item_group": "Productos", 
  "item_name": "MOUSE GENIUS", 
  "item_tax_rate": "{}", 
  "material_request": null, 
  "material_request_item": null, 
  "modified": "2017-06-06 11:33:21.688649", 
  "name": "ae11f89bee", 
  "net_amount": 36.0, 
  "net_rate": 12.0, 
  "page_break": 0, 
  "price_list_rate": 12.0, 
  "pricing_rule": null, 
  "project": null, 
  "qty": 3.0, 
  "rate": 12.0, 
  "received_qty": 0.0, 
  "returned_qty": 0.0, 
  "sales_order": null, 
  "sales_order_item": null, 
  "schedule_date": "2017-06-06", 
  "stock_qty": 3.0, 
  "stock_uom": "Unidad(es)", 
  "subtotal": 36.0, 
  "supplier_part_no": null, 
  "supplier_quotation": null, 
  "supplier_quotation_item": null, 
  "unit_price": 12.0, 
  "unit_price_with_no_dcto": 12.0, 
  "unit_price_with_tax": 17.784, 
  "uom": "Unidad(es)", 
  "warehouse": "Sucursales - ET"
 }, 
 {
  "amount": 0.0, 
  "base_amount": 0.0, 
  "base_net_amount": 0.0, 
  "base_net_rate": 0.0, 
  "base_price_list_rate": 0.0, 
  "base_rate": 0.0, 
  "billed_amt": 0.0, 
  "bom": null, 
  "brand": "TOSHIBA", 
  "conversion_factor": 1.0, 
  "delivered_by_supplier": 0, 
  "description": "PORT\u00c1TIL TOSHIBA", 
  "discount": 0.0, 
  "discount_percentage": 0.0, 
  "docstatus": 1, 
  "doctype": "Purchase Order Item", 
  "expected_delivery_date": null, 
  "image": "", 
  "item_code": "PT0001", 
  "item_group": "Productos", 
  "item_name": "PORT\u00c1TIL TOSHIBA", 
  "item_tax_rate": "{\"IVA 14 - ET\": 14.0}", 
  "material_request": null, 
  "material_request_item": null, 
  "modified": "2017-06-06 11:33:21.688649", 
  "name": "56a06593a1", 
  "net_amount": 0.0, 
  "net_rate": 0.0, 
  "page_break": 0, 
  "price_list_rate": 0.0, 
  "pricing_rule": null, 
  "project": null, 
  "qty": 1.0, 
  "rate": 0.0, 
  "received_qty": 0.0, 
  "returned_qty": 0.0, 
  "sales_order": null, 
  "sales_order_item": null, 
  "schedule_date": "2017-06-06", 
  "stock_qty": 1.0, 
  "stock_uom": "Unidad(es)", 
  "subtotal": 800.0, 
  "supplier_part_no": null, 
  "supplier_quotation": null, 
  "supplier_quotation_item": null, 
  "unit_price": 800.0, 
  "unit_price_with_no_dcto": 800.0, 
  "unit_price_with_tax": 1185.6, 
  "uom": "Unidad(es)", 
  "warehouse": "Sucursales - ET"
 }, 
 {
  "amount": 450.0, 
  "base_amount": 450.0, 
  "base_net_amount": 450.0, 
  "base_net_rate": 450.0, 
  "base_price_list_rate": 450.0, 
  "base_rate": 450.0, 
  "billed_amt": 0.0, 
  "bom": null, 
  "brand": "HP", 
  "conversion_factor": 1.0, 
  "delivered_by_supplier": 0, 
  "description": "PORT\u00c1TIL HP", 
  "discount": 0.0, 
  "discount_percentage": 0.0, 
  "docstatus": 1, 
  "doctype": "Purchase Order Item", 
  "expected_delivery_date": null, 
  "image": "", 
  "item_code": "HP-COREI3", 
  "item_group": "Productos", 
  "item_name": "HP-COREI3", 
  "item_tax_rate": "{}", 
  "material_request": null, 
  "material_request_item": null, 
  "modified": "2017-06-06 12:01:19.163770", 
  "name": "357abb06e6", 
  "net_amount": 450.0, 
  "net_rate": 450.0, 
  "page_break": 0, 
  "price_list_rate": 450.0, 
  "pricing_rule": null, 
  "project": null, 
  "qty": 1.0, 
  "rate": 450.0, 
  "received_qty": 0.0, 
  "returned_qty": 0.0, 
  "sales_order": null, 
  "sales_order_item": null, 
  "schedule_date": "2017-06-06", 
  "stock_qty": 1.0, 
  "stock_uom": "Unidad(es)", 
  "subtotal": 450.0, 
  "supplier_part_no": null, 
  "supplier_quotation": null, 
  "supplier_quotation_item": null, 
  "unit_price": 450.0, 
  "unit_price_with_no_dcto": 450.0, 
  "unit_price_with_tax": 666.9, 
  "uom": "Unidad(es)", 
  "warehouse": "Sucursales - ET"
 }, 
 {
  "amount": 144.0, 
  "base_amount": 144.0, 
  "base_net_amount": 144.0, 
  "base_net_rate": 12.0, 
  "base_price_list_rate": 12.0, 
  "base_rate": 12.0, 
  "billed_amt": 0.0, 
  "bom": null, 
  "brand": "GENIUS", 
  "conversion_factor": 1.0, 
  "delivered_by_supplier": 0, 
  "description": "MOUSE GENIUS", 
  "discount": 0.0, 
  "discount_percentage": 0.0, 
  "docstatus": 1, 
  "doctype": "Purchase Order Item", 
  "expected_delivery_date": null, 
  "image": "", 
  "item_code": "PM0001", 
  "item_group": "Productos", 
  "item_name": "MOUSE GENIUS", 
  "item_tax_rate": "{}", 
  "material_request": null, 
  "material_request_item": null, 
  "modified": "2017-06-06 12:37:24.466978", 
  "name": "faa416dd58", 
  "net_amount": 144.0, 
  "net_rate": 12.0, 
  "page_break": 0, 
  "price_list_rate": 12.0, 
  "pricing_rule": null, 
  "project": null, 
  "qty": 12.0, 
  "rate": 12.0, 
  "received_qty": 0.0, 
  "returned_qty": 0.0, 
  "sales_order": null, 
  "sales_order_item": null, 
  "schedule_date": "2017-06-06", 
  "stock_qty": 12.0, 
  "stock_uom": "Unidad(es)", 
  "subtotal": 144.0, 
  "supplier_part_no": null, 
  "supplier_quotation": null, 
  "supplier_quotation_item": null, 
  "unit_price": 12.0, 
  "unit_price_with_no_dcto": 12.0, 
  "unit_price_with_tax": 17.784, 
  "uom": "Unidad(es)", 
  "warehouse": "Sucursales - ET"
 }, 
 {
  "amount": 102.0, 
  "base_amount": 102.0, 
  "base_net_amount": 102.0, 
  "base_net_rate": 34.0, 
  "base_price_list_rate": 34.0, 
  "base_rate": 34.0, 
  "billed_amt": 0.0, 
  "bom": null, 
  "brand": null, 
  "conversion_factor": 1.0, 
  "delivered_by_supplier": 0, 
  "description": "PORT\u00c1TIL DELL", 
  "discount": 0.0, 
  "discount_percentage": 0.0, 
  "docstatus": 1, 
  "doctype": "Purchase Order Item", 
  "expected_delivery_date": null, 
  "image": "", 
  "item_code": "PORT\u00c1TIL DELL", 
  "item_group": "Productos", 
  "item_name": "PORT\u00c1TIL DELL", 
  "item_tax_rate": "{}", 
  "material_request": null, 
  "material_request_item": null, 
  "modified": "2017-06-06 12:47:57.965458", 
  "name": "6ad33ccb50", 
  "net_amount": 102.0, 
  "net_rate": 34.0, 
  "page_break": 0, 
  "price_list_rate": 34.0, 
  "pricing_rule": null, 
  "project": null, 
  "qty": 3.0, 
  "rate": 34.0, 
  "received_qty": 0.0, 
  "returned_qty": 0.0, 
  "sales_order": null, 
  "sales_order_item": null, 
  "schedule_date": "2017-06-06", 
  "stock_qty": 3.0, 
  "stock_uom": "Unidad(es)", 
  "subtotal": 1500.0, 
  "supplier_part_no": null, 
  "supplier_quotation": null, 
  "supplier_quotation_item": null, 
  "unit_price": 500.0, 
  "unit_price_with_no_dcto": 500.0, 
  "unit_price_with_tax": 741.0, 
  "uom": "Unidad(es)", 
  "warehouse": "Productos terminados - ET"
 }, 
 {
  "amount": 900.0, 
  "base_amount": 900.0, 
  "base_net_amount": 900.0, 
  "base_net_rate": 450.0, 
  "base_price_list_rate": 450.0, 
  "base_rate": 450.0, 
  "billed_amt": 0.0, 
  "bom": null, 
  "brand": "HP", 
  "conversion_factor": 1.0, 
  "delivered_by_supplier": 0, 
  "description": "PORT\u00c1TIL HP", 
  "discount": 0.0, 
  "discount_percentage": 0.0, 
  "docstatus": 1, 
  "doctype": "Purchase Order Item", 
  "expected_delivery_date": null, 
  "image": "", 
  "item_code": "HP-COREI3", 
  "item_group": "Productos", 
  "item_name": "HP-COREI3", 
  "item_tax_rate": "{}", 
  "material_request": null, 
  "material_request_item": null, 
  "modified": "2017-06-06 14:48:16.272496", 
  "name": "029ed2dbd0", 
  "net_amount": 900.0, 
  "net_rate": 450.0, 
  "page_break": 0, 
  "price_list_rate": 450.0, 
  "pricing_rule": null, 
  "project": null, 
  "qty": 2.0, 
  "rate": 450.0, 
  "received_qty": 0.0, 
  "returned_qty": 0.0, 
  "sales_order": null, 
  "sales_order_item": null, 
  "schedule_date": "2017-06-06", 
  "stock_qty": 2.0, 
  "stock_uom": "Unidad(es)", 
  "subtotal": 900.0, 
  "supplier_part_no": null, 
  "supplier_quotation": null, 
  "supplier_quotation_item": null, 
  "unit_price": 450.0, 
  "unit_price_with_no_dcto": 450.0, 
  "unit_price_with_tax": 666.9, 
  "uom": "Unidad(es)", 
  "warehouse": "Sucursales - ET"
 }, 
 {
  "amount": 1800.0, 
  "base_amount": 1800.0, 
  "base_net_amount": 1800.0, 
  "base_net_rate": 450.0, 
  "base_price_list_rate": 450.0, 
  "base_rate": 450.0, 
  "billed_amt": 0.0, 
  "bom": null, 
  "brand": "HP", 
  "conversion_factor": 1.0, 
  "delivered_by_supplier": 0, 
  "description": "PORT\u00c1TIL HP", 
  "discount": 0.0, 
  "discount_percentage": 0.0, 
  "docstatus": 1, 
  "doctype": "Purchase Order Item", 
  "expected_delivery_date": null, 
  "image": "", 
  "item_code": "HP-COREI3", 
  "item_group": "Productos", 
  "item_name": "HP-COREI3", 
  "item_tax_rate": "{}", 
  "material_request": null, 
  "material_request_item": null, 
  "modified": "2017-06-06 14:52:04.879550", 
  "name": "c6db9a8d14", 
  "net_amount": 1800.0, 
  "net_rate": 450.0, 
  "page_break": 0, 
  "price_list_rate": 450.0, 
  "pricing_rule": null, 
  "project": null, 
  "qty": 4.0, 
  "rate": 450.0, 
  "received_qty": 0.0, 
  "returned_qty": 0.0, 
  "sales_order": null, 
  "sales_order_item": null, 
  "schedule_date": "2017-06-06", 
  "stock_qty": 4.0, 
  "stock_uom": "Unidad(es)", 
  "subtotal": 1800.0, 
  "supplier_part_no": null, 
  "supplier_quotation": null, 
  "supplier_quotation_item": null, 
  "unit_price": 450.0, 
  "unit_price_with_no_dcto": 450.0, 
  "unit_price_with_tax": 666.9, 
  "uom": "Unidad(es)", 
  "warehouse": "Sucursales - ET"
 }, 
 {
  "amount": 0.0, 
  "base_amount": 0.0, 
  "base_net_amount": 0.0, 
  "base_net_rate": 0.0, 
  "base_price_list_rate": 0.0, 
  "base_rate": 0.0, 
  "billed_amt": 0.0, 
  "bom": null, 
  "brand": "TOSHIBA", 
  "conversion_factor": 1.0, 
  "delivered_by_supplier": 0, 
  "description": "PORT\u00c1TIL TOSHIBA", 
  "discount": 0.0, 
  "discount_percentage": 0.0, 
  "docstatus": 1, 
  "doctype": "Purchase Order Item", 
  "expected_delivery_date": null, 
  "image": "", 
  "item_code": "PT0001", 
  "item_group": "Productos", 
  "item_name": "PORT\u00c1TIL TOSHIBA", 
  "item_tax_rate": "{\"IVA 14 - ET\": 14.0}", 
  "material_request": null, 
  "material_request_item": null, 
  "modified": "2017-06-06 16:30:38.152523", 
  "name": "ed611a4da4", 
  "net_amount": 0.0, 
  "net_rate": 0.0, 
  "page_break": 0, 
  "price_list_rate": 0.0, 
  "pricing_rule": null, 
  "project": null, 
  "qty": 3.0, 
  "rate": 0.0, 
  "received_qty": 0.0, 
  "returned_qty": 0.0, 
  "sales_order": null, 
  "sales_order_item": null, 
  "schedule_date": "2017-06-06", 
  "stock_qty": 3.0, 
  "stock_uom": "Unidad(es)", 
  "subtotal": 2400.0, 
  "supplier_part_no": null, 
  "supplier_quotation": null, 
  "supplier_quotation_item": null, 
  "unit_price": 800.0, 
  "unit_price_with_no_dcto": 800.0, 
  "unit_price_with_tax": 1185.6, 
  "uom": "Unidad(es)", 
  "warehouse": "Sucursales - ET"
 }, 
 {
  "amount": 34.0, 
  "base_amount": 34.0, 
  "base_net_amount": 34.0, 
  "base_net_rate": 34.0, 
  "base_price_list_rate": 34.0, 
  "base_rate": 34.0, 
  "billed_amt": 0.0, 
  "bom": null, 
  "brand": null, 
  "conversion_factor": 1.0, 
  "delivered_by_supplier": 0, 
  "description": "PORT\u00c1TIL DELL", 
  "discount": 0.0, 
  "discount_percentage": 0.0, 
  "docstatus": 1, 
  "doctype": "Purchase Order Item", 
  "expected_delivery_date": null, 
  "image": "", 
  "item_code": "PORT\u00c1TIL DELL", 
  "item_group": "Productos", 
  "item_name": "PORT\u00c1TIL DELL", 
  "item_tax_rate": "{}", 
  "material_request": null, 
  "material_request_item": null, 
  "modified": "2017-06-06 17:35:57.216359", 
  "name": "0cc8fa6705", 
  "net_amount": 34.0, 
  "net_rate": 34.0, 
  "page_break": 0, 
  "price_list_rate": 34.0, 
  "pricing_rule": null, 
  "project": null, 
  "qty": 1.0, 
  "rate": 34.0, 
  "received_qty": 0.0, 
  "returned_qty": 0.0, 
  "sales_order": null, 
  "sales_order_item": null, 
  "schedule_date": "2017-06-06", 
  "stock_qty": 1.0, 
  "stock_uom": "Unidad(es)", 
  "subtotal": 500.0, 
  "supplier_part_no": null, 
  "supplier_quotation": null, 
  "supplier_quotation_item": null, 
  "unit_price": 500.0, 
  "unit_price_with_no_dcto": 500.0, 
  "unit_price_with_tax": 741.0, 
  "uom": "Unidad(es)", 
  "warehouse": "Productos terminados - ET"
 }, 
 {
  "amount": 0.0, 
  "base_amount": 0.0, 
  "base_net_amount": 0.0, 
  "base_net_rate": 0.0, 
  "base_price_list_rate": 0.0, 
  "base_rate": 0.0, 
  "billed_amt": 0.0, 
  "bom": null, 
  "brand": "TOSHIBA", 
  "conversion_factor": 1.0, 
  "delivered_by_supplier": 0, 
  "description": "PORT\u00c1TIL TOSHIBA", 
  "discount": 0.0, 
  "discount_percentage": 0.0, 
  "docstatus": 1, 
  "doctype": "Purchase Order Item", 
  "expected_delivery_date": null, 
  "image": "", 
  "item_code": "PT0001", 
  "item_group": "Productos", 
  "item_name": "PORT\u00c1TIL TOSHIBA", 
  "item_tax_rate": "{\"IVA 14 - ET\": 14.0}", 
  "material_request": null, 
  "material_request_item": null, 
  "modified": "2017-06-06 18:02:33.616784", 
  "name": "0706a5703d", 
  "net_amount": 0.0, 
  "net_rate": 0.0, 
  "page_break": 0, 
  "price_list_rate": 0.0, 
  "pricing_rule": null, 
  "project": null, 
  "qty": 3.0, 
  "rate": 0.0, 
  "received_qty": 0.0, 
  "returned_qty": 0.0, 
  "sales_order": null, 
  "sales_order_item": null, 
  "schedule_date": "2017-06-06", 
  "stock_qty": 3.0, 
  "stock_uom": "Unidad(es)", 
  "subtotal": 2400.0, 
  "supplier_part_no": null, 
  "supplier_quotation": null, 
  "supplier_quotation_item": null, 
  "unit_price": 800.0, 
  "unit_price_with_no_dcto": 800.0, 
  "unit_price_with_tax": 1185.6, 
  "uom": "Unidad(es)", 
  "warehouse": "Sucursales - ET"
 }
]